wdl/__init__.py
wdl/build_wdl_fp_v0.py
wdl/build_wdl_fp_v2.py
wdl/build_wdl_net_v0.py
wdl/build_wdl_net_v2.py
wdl/demo_predict.py
wdl/demo_predict_v2.py
wdl/demo_train.py
wdl/demo_train_tr.py
wdl/demo_train_v2.py
wdl/features.py
wdl/mol_graph.py
wdl/optimizers.py
wdl/rdkit_utils.py
wdl/run_utils.py
wdl/util.py
wdl/data/A1.csv
wdl/data/A2.csv
wdl/data/A3.csv
wdl/data/A4.csv
wdl/data/A5.csv
wdl/data/AS1.csv
wdl/data/AS2.csv
wdl_rf-0.0.15.dist-info/LICENSE
wdl_rf-0.0.15.dist-info/METADATA
wdl_rf-0.0.15.dist-info/WHEEL
wdl_rf-0.0.15.dist-info/top_level.txt
wdl_rf-0.0.15.dist-info/RECORD
